.coveragerc
AUTHORS
ChangeLog
LICENSE
README.rst
setup.cfg
setup.py
tox.ini
deuce_valere.egg-info/PKG-INFO
deuce_valere.egg-info/SOURCES.txt
deuce_valere.egg-info/dependency_links.txt
deuce_valere.egg-info/entry_points.txt
deuce_valere.egg-info/not-zip-safe
deuce_valere.egg-info/requires.txt
deuce_valere.egg-info/top_level.txt
deucevalere/__init__.py
deucevalere/shell.py
deucevalere/api/__init__.py
deucevalere/api/auth.py
deucevalere/api/shell_cache.py
deucevalere/api/system.py
deucevalere/client/valere.py
deucevalere/common/validation.py
deucevalere/common/validation_instance.py
deucevalere/splitter/__init__.py
deucevalere/splitter/meta_splitter.py
deucevalere/tests/__init__.py
deucevalere/tests/client_base.py
deucevalere/tests/test_api_shell_cache.py
deucevalere/tests/test_api_system_counter_manager.py
deucevalere/tests/test_api_system_list_manager.py
deucevalere/tests/test_api_system_manager.py
deucevalere/tests/test_api_system_manager_serialize.py
deucevalere/tests/test_api_system_time_manager.py
deucevalere/tests/test_client_valere.py
deucevalere/tests/test_client_valere_block_retrieval.py
deucevalere/tests/test_client_valere_build_cross_reference.py
deucevalere/tests/test_client_valere_cleanup_expired.py
deucevalere/tests/test_client_valere_cleanup_orphaned.py
deucevalere/tests/test_client_valere_validate_metadata.py
deucevalere/tests/test_client_valere_validate_storage.py
deucevalere/tests/test_client_valere_validate_storage_with_head.py
deucevalere/tests/test_convenience_functions_cleanup.py
deucevalere/tests/test_convenience_functions_reload.py
deucevalere/tests/test_convenience_functions_validation.py
deucevalere/tests/test_splitter.py
deucevalere/tests/test_validation.py
deucevalere/tests/test_validation_instance.py
deucevalere/tests/test_version.py
tools/pip-requires
tools/test-requirements.txt