Metadata-Version: 1.1
Name: deuce-valere
Version: 0.1-beta1.dev74.ge9ba7d9
Summary: Validation Client Functionality for Deuce De-Duplication-As-A-Service
Home-page: http://github.com/rackerlabs/deuce-valere
Author: Rackspace
Author-email: UNKNOWN
License: Apache-2
Platform: UNKNOWN
Classifier: Development Status :: 3 - Alpha
Classifier: Environment :: Console
Classifier: Environment :: OpenStack
Classifier: Intended Audience :: Developers
Classifier: Intended Audience :: Information Technology
Classifier: Intended Audience :: System Administrators
Classifier: License :: OSI Approved :: Apache Software License
Classifier: Operating System :: OS Independent
Classifier: Operating System :: POSIX :: Linux
Classifier: Programming Language :: Python
Classifier: Programming Language :: Python :: 3
Classifier: Programming Language :: Python :: 3.3
Classifier: Programming Language :: Python :: 3.4
